[{"department_ids": [48, 53], "name": "Engineering and the Rise of Modern Industry", "id": 461, "number": ""}, {"department_ids": [48], "name": "Signals and Systems", "id": 2340, "number": "ELEN 3801"}, {"department_ids": [48], "name": "Introduction to Network Engineering, Elements of Digital System", "id": 3311, "number": null}, {"department_ids": [48], "name": "Intro to Communication System", "id": 3333, "number": "ELEN 3701"}, {"department_ids": [48], "name": "Circuit Analysis", "id": 3551, "number": "ELEN 3201"}, {"department_ids": [48], "name": "Electronic Circuits", "id": 3672, "number": "ELEN 3331"}, {"department_ids": [48], "name": "Electromagnetics", "id": 3687, "number": "ELEN 3401"}, {"department_ids": [48], "name": "Digital Image Processing", "id": 3688, "number": "ELEN 4830"}, {"department_ids": [48], "name": "Genomic Info Science & Technology", "id": 4010, "number": null}, {"department_ids": [48], "name": "RIse of Technology....", "id": 4076, "number": null}, {"department_ids": [48], "name": "Intro to Electrical Engineering", "id": 4125, "number": "ELEN 1201"}, {"department_ids": [48], "name": "Probability", "id": 4127, "number": "SIEO 3658"}, {"department_ids": [7, 48], "name": "Fundamentals of Computer Systems", "id": 4251, "number": "CSEE W3827"}, {"department_ids": [48], "name": "Circuit Design Capstone Lab", "id": 4259, "number": "ELEN 3390"}, {"department_ids": [48], "name": "Digital Signal Processing", "id": 5099, "number": "ELEN E4810"}, {"department_ids": [48], "name": "Wireless and Mobile Networking I", "id": 5112, "number": "ELEN E6950"}, {"department_ids": [48], "name": "Digital Communications", "id": 5124, "number": "ELEN 4702"}, {"department_ids": [48], "name": "Solid-state devices and materials", "id": 5182, "number": "ELEN 3106"}, {"department_ids": [48], "name": "Fundamentals of Photonics", "id": 5274, "number": "ELEN E4411"}, {"department_ids": [48], "name": "The Digital Information Age", "id": 5311, "number": "ELEN 1101"}, {"department_ids": [48], "name": "Device Nanofabrication", "id": 5335, "number": "ELEN E6945"}, {"department_ids": [48], "name": "Wave Transmission and Fiber Optics", "id": 5362, "number": "ELEN 4401"}, {"department_ids": [48], "name": "Solid State, Microwave, and Fiber Optics Lab", "id": 5508, "number": "ELEN E3043"}, {"department_ids": [48], "name": "Introduction to Control Theory", "id": 5561, "number": "EEME E6601"}, {"department_ids": [48], "name": "Wireless Communications", "id": 5667, "number": "ELEN E4703"}, {"department_ids": [48], "name": "Analog Electronic Circuits", "id": 5827, "number": "ELEN E4312"}, {"department_ids": [48], "name": "Random Signals & Noise", "id": 6242, "number": "ELEN E4815"}, {"department_ids": [48], "name": "Data Compression", "id": 6359, "number": "E6884"}, {"department_ids": [48], "name": "Power System Analysis", "id": 6611, "number": "ELEN E4511"}, {"department_ids": [48], "name": "Digital VLSI Circuits", "id": 6708, "number": "EECS E4321"}]