[{"first_name": "Brian", "last_name": "Morton", "id": 408, "middle_name": "", "nugget": "None"}, {"first_name": "Jeanne", "last_name": "Poindexter", "id": 615, "middle_name": "", "nugget": "None"}, {"first_name": "Rafael", "last_name": "Yuste", "id": 688, "middle_name": "", "nugget": "None"}, {"first_name": "Philip", "last_name": "Ammirato", "id": 706, "middle_name": "", "nugget": "None"}, {"first_name": "Judith", "last_name": "Gibber", "id": 733, "middle_name": "", "nugget": "None"}, {"first_name": "Martin", "last_name": "Chalfie", "id": 734, "middle_name": "", "nugget": "Silver"}, {"first_name": "John", "last_name": "Glendinning", "id": 953, "middle_name": "", "nugget": "None"}, {"first_name": "Carol", "last_name": "Lin", "id": 957, "middle_name": "", "nugget": "None"}, {"first_name": "Stuart", "last_name": "Firestein", "id": 961, "middle_name": "", "nugget": "None"}, {"first_name": "Claire Elise", "last_name": "Hazen", "id": 1015, "middle_name": "", "nugget": "Silver"}, {"first_name": "Robert", "last_name": "Pollack", "id": 1021, "middle_name": "", "nugget": "None"}, {"first_name": "Paul", "last_name": "Hertz", "id": 1044, "middle_name": "", "nugget": "Silver"}, {"first_name": "Edward", "last_name": "Ciaccio", "id": 1121, "middle_name": "", "nugget": "None"}, {"first_name": "Walter", "last_name": "Bock", "id": 1122, "middle_name": "", "nugget": "None"}, {"first_name": "Helen", "last_name": "Lu", "id": 1123, "middle_name": "", "nugget": "None"}, {"first_name": "Geoffrey", "last_name": "Zubay", "id": 1137, "middle_name": "", "nugget": "None"}, {"first_name": "Ron", "last_name": "Prywes", "id": 1139, "middle_name": "", "nugget": "None"}, {"first_name": "Kevin", "last_name": "Costa", "id": 1178, "middle_name": "", "nugget": "Silver"}, {"first_name": "Jack", "last_name": "McGourty", "id": 1418, "middle_name": "", "nugget": "None"}, {"first_name": "Alvin", "last_name": "Wald", "id": 1483, "middle_name": "", "nugget": "None"}, {"first_name": "John", "last_name": "Loike", "id": 1561, "middle_name": "", "nugget": "None"}, {"first_name": "Jeffrey", "last_name": "Holmes", "id": 1732, "middle_name": "", "nugget": "None"}, {"first_name": "Stiliana", "last_name": "Antonova", "id": 1770, "middle_name": "", "nugget": "None"}, {"first_name": "Kristen", "last_name": "Shepard", "id": 1855, "middle_name": "", "nugget": "Silver"}, {"first_name": "Jian", "last_name": "Yang", "id": 1859, "middle_name": "", "nugget": "None"}, {"first_name": "Darcy", "last_name": "Kelley", "id": 1955, "middle_name": "", "nugget": "Silver"}, {"first_name": "Alvin", "last_name": "Krasna", "id": 1963, "middle_name": "", "nugget": "None"}, {"first_name": "James", "last_name": "Danoff-Burg", "id": 2125, "middle_name": "", "nugget": "None"}, {"first_name": "Shao-Ying", "last_name": "Hua", "id": 2141, "middle_name": "", "nugget": "Silver"}, {"first_name": "Barclay", "last_name": "Morrison", "id": 2235, "middle_name": "", "nugget": "None"}, {"first_name": "Jessica", "last_name": "Goldstein", "id": 2296, "middle_name": "", "nugget": "None"}, {"first_name": "Lance", "last_name": "Kam", "id": 2306, "middle_name": "", "nugget": "None"}, {"first_name": "Clark", "last_name": "Hung", "id": 2368, "middle_name": "", "nugget": "None"}, {"first_name": "Sally", "last_name": "Aboelela", "id": 2437, "middle_name": "", "nugget": "None"}, {"first_name": "Alice", "last_name": "Heicklen", "id": 2525, "middle_name": "", "nugget": "None"}, {"first_name": "Julio", "last_name": "Fernandez", "id": 2595, "middle_name": "", "nugget": "Silver"}, {"first_name": "Amer", "last_name": "Beg", "id": 2622, "middle_name": "", "nugget": "None"}, {"first_name": "Liang", "last_name": "Tong", "id": 2626, "middle_name": "", "nugget": "None"}, {"first_name": "Daniel", "last_name": "Aviv", "id": 2647, "middle_name": "", "nugget": "None"}, {"first_name": "Deborah", "last_name": "Mowshowitz", "id": 2673, "middle_name": "", "nugget": "None"}, {"first_name": "Wanda", "last_name": "Knauss", "id": 2675, "middle_name": "", "nugget": "None"}, {"first_name": "Alexandra", "last_name": "Horowitz", "id": 2678, "middle_name": "", "nugget": "Silver"}, {"first_name": "Brent", "last_name": "Stockwell", "id": 2753, "middle_name": "", "nugget": "None"}, {"first_name": "Matthew", "last_name": "Wallenfang", "id": 2859, "middle_name": "", "nugget": "None"}, {"first_name": "Elizabeth", "last_name": "Miller", "id": 2861, "middle_name": "", "nugget": "Silver"}, {"first_name": "Matthew", "last_name": "Birck", "id": 2919, "middle_name": "", "nugget": "None"}, {"first_name": "Hilary", "last_name": "Callahan", "id": 2999, "middle_name": "", "nugget": "None"}, {"first_name": "Carol", "last_name": "Prives", "id": 3030, "middle_name": "", "nugget": "None"}, {"first_name": "Elizabeth", "last_name": "Hillman", "id": 3098, "middle_name": "", "nugget": "None"}, {"first_name": "Stiliana", "last_name": "Savin", "id": 3105, "middle_name": "", "nugget": "None"}, {"first_name": "Alexander", "last_name": "Tzagoloff", "id": 3133, "middle_name": "", "nugget": "None"}, {"first_name": "Daniel", "last_name": "Kalderon", "id": 3286, "middle_name": "", "nugget": "None"}, {"first_name": "David H.", "last_name": "Newman", "id": 3365, "middle_name": "", "nugget": "None"}, {"first_name": "James", "last_name": "Russo", "id": 3495, "middle_name": "", "nugget": "None"}, {"first_name": "Lawrence", "last_name": "Chasin", "id": 4007, "middle_name": "", "nugget": "None"}, {"first_name": "Ron", "last_name": "Guido", "id": 4009, "middle_name": null, "nugget": "None"}, {"first_name": "James", "last_name": "Manley", "id": 4012, "middle_name": "L", "nugget": "None"}, {"first_name": "Yin Mei", "last_name": "Lim", "id": 4015, "middle_name": "", "nugget": "None"}, {"first_name": "Solomon", "last_name": "Mowshowitz", "id": 4016, "middle_name": null, "nugget": "Silver"}, {"first_name": "Songtao", "last_name": "Jia", "id": 4017, "middle_name": null, "nugget": "None"}, {"first_name": "Jennifer", "last_name": "Mansfield", "id": 4023, "middle_name": null, "nugget": "None"}, {"first_name": "Elizabeth", "last_name": "Bauer", "id": 4024, "middle_name": null, "nugget": "None"}, {"first_name": "X.", "last_name": "Guo", "id": 4028, "middle_name": "Edward", "nugget": "None"}, {"first_name": "Andreas", "last_name": "Hielscher", "id": 4029, "middle_name": null, "nugget": "None"}, {"first_name": "Paul", "last_name": "Sajda", "id": 4034, "middle_name": null, "nugget": "None"}, {"first_name": "Vincent", "last_name": "Racaniello", "id": 5567, "middle_name": "R", "nugget": "Silver"}, {"first_name": "Chloe", "last_name": "Bulinski", "id": 7496, "middle_name": "J", "nugget": "None"}, {"first_name": "Nora", "last_name": "Ovtcharova", "id": 9353, "middle_name": "", "nugget": "None"}, {"first_name": "Dominique", "last_name": "Toran-Allerand", "id": 9384, "middle_name": "", "nugget": "None"}, {"first_name": "Julia", "last_name": "Sable", "id": 9465, "middle_name": null, "nugget": "None"}, {"first_name": "Henry", "last_name": "Hess", "id": 9469, "middle_name": null, "nugget": "None"}, {"first_name": "Nataliya", "last_name": "Galifianakis", "id": 10162, "middle_name": null, "nugget": "None"}, {"first_name": "Brenda", "last_name": "Perez", "id": 10163, "middle_name": "", "nugget": "None"}, {"first_name": "Zafir", "last_name": "Buraei", "id": 10697, "middle_name": null, "nugget": "None"}, {"first_name": "David", "last_name": "Sable", "id": 10698, "middle_name": null, "nugget": "None"}, {"first_name": "Diana", "last_name": "Heller", "id": 10699, "middle_name": null, "nugget": "None"}, {"first_name": "Mitchell", "last_name": "Hayes", "id": 11203, "middle_name": "", "nugget": "None"}, {"first_name": "Jessica ", "last_name": "Brann", "id": 11347, "middle_name": "", "nugget": "None"}, {"first_name": "Jessica", "last_name": "Brann", "id": 11379, "middle_name": "", "nugget": "None"}, {"first_name": "David", "last_name": "Vawdrey", "id": 12820, "middle_name": "", "nugget": "None"}, {"first_name": "Jennifer", "last_name": "Punt", "id": 12941, "middle_name": "", "nugget": "None"}, {"first_name": "Darpan", "last_name": "Patel", "id": 12943, "middle_name": "", "nugget": "None"}, {"first_name": "Matt", "last_name": "Welsch", "id": 12944, "middle_name": "", "nugget": "None"}, {"first_name": "Thomas", "last_name": "Wang", "id": 12945, "middle_name": "", "nugget": "None"}]