[{"last_name": "Mesznik", "nugget": "None", "first_name": "Roger", "middle_name": "", "id": 390}, {"last_name": "Rabinowitz", "nugget": "None", "first_name": "Daniel", "middle_name": "", "id": 500}, {"last_name": "Weinig", "nugget": "Silver", "first_name": "Sheldon", "middle_name": "", "id": 913}, {"last_name": "Dayanik", "nugget": "None", "first_name": "Savas", "middle_name": "", "id": 1066}, {"last_name": "Sigman", "nugget": "Silver", "first_name": "Karl", "middle_name": "", "id": 1147}, {"last_name": "Kou", "nugget": "None", "first_name": "Steven", "middle_name": "", "id": 1176}, {"last_name": "Haugh", "nugget": "None", "first_name": "Martin", "middle_name": "", "id": 1215}, {"last_name": "Riccio", "nugget": "None", "first_name": "Lucius", "middle_name": "", "id": 1226}, {"last_name": "Stein", "nugget": "None", "first_name": "Clifford", "middle_name": "", "id": 1342}, {"last_name": "Petrella", "nugget": "None", "first_name": "Giovanni", "middle_name": "", "id": 1410}, {"last_name": "McGourty", "nugget": "None", "first_name": "Jack", "middle_name": "", "id": 1418}, {"last_name": "Eck", "nugget": "None", "first_name": "Brian", "middle_name": "", "id": 1660}, {"last_name": "Whitt", "nugget": "None", "first_name": "Ward", "middle_name": "", "id": 1666}, {"last_name": "Shahabuddin", "nugget": "None", "first_name": "Perwez", "middle_name": "", "id": 1760}, {"last_name": "Loh", "nugget": "None", "first_name": "Ji Meng", "middle_name": "", "id": 1785}, {"last_name": "Heyman", "nugget": "None", "first_name": "Dan", "middle_name": "", "id": 1995}, {"last_name": "Sethuraman", "nugget": "None", "first_name": "Jay", "middle_name": "", "id": 2026}, {"last_name": "Huh", "nugget": "None", "first_name": "Tim", "middle_name": "", "id": 2076}, {"last_name": "Wright", "nugget": "None", "first_name": "Larry", "middle_name": "", "id": 2277}, {"last_name": "Kachani", "nugget": "None", "first_name": "Soulaymane", "middle_name": "", "id": 2319}, {"last_name": "Mihaila", "nugget": "None", "first_name": "George", "middle_name": "", "id": 2332}, {"last_name": "Gallego", "nugget": "None", "first_name": "Guillermo", "middle_name": "", "id": 2497}, {"last_name": "Iyengar", "nugget": "None", "first_name": "Garud", "middle_name": "", "id": 2521}, {"last_name": "Hogan", "nugget": "None", "first_name": "Michael", "middle_name": "", "id": 2526}, {"last_name": "Brown", "nugget": "None", "first_name": "Mark", "middle_name": "", "id": 2531}, {"last_name": "Latzko", "nugget": "Silver", "first_name": "William", "middle_name": "", "id": 2590}, {"last_name": "Juneja", "nugget": "None", "first_name": "Sandeep", "middle_name": "", "id": 2617}, {"last_name": "Shapiro", "nugget": "None", "first_name": "Paul", "middle_name": "", "id": 2636}, {"last_name": "Yao", "nugget": "Silver", "first_name": "David", "middle_name": "", "id": 2683}, {"last_name": "Paninski", "nugget": "None", "first_name": "Liam", "middle_name": "", "id": 2731}, {"last_name": "Guirguis", "nugget": "None", "first_name": "Hany", "middle_name": "", "id": 2755}, {"last_name": "Norden", "nugget": "None", "first_name": "Peter", "middle_name": "", "id": 2770}, {"last_name": "Dehnad", "nugget": "None", "first_name": "Kozrow", "middle_name": "", "id": 3125}, {"last_name": "Dehnad", "nugget": "None", "first_name": "Khosrow", "middle_name": "", "id": 3157}, {"last_name": "Olvera-Cravioto", "nugget": "None", "first_name": "Mariana", "middle_name": "", "id": 3158}, {"last_name": "Le Guyader", "nugget": "Silver", "first_name": "Louis", "middle_name": "", "id": 3222}, {"last_name": "Gold", "nugget": "Silver", "first_name": "Leon", "middle_name": "", "id": 3375}, {"last_name": "Mongeot", "nugget": "None", "first_name": "Dimitri", "middle_name": "", "id": 3391}, {"last_name": "Webster", "nugget": "Silver", "first_name": "Anthony", "middle_name": "C", "id": 3815}, {"last_name": "Blanchet", "nugget": "None", "first_name": "Jose", "middle_name": null, "id": 4995}, {"last_name": "Chudnovsky", "nugget": "None", "first_name": "Maria", "middle_name": null, "id": 4996}, {"last_name": "Cont", "nugget": "None", "first_name": "Rama", "middle_name": null, "id": 4997}, {"last_name": "Goldfarb", "nugget": "None", "first_name": "Donald", "middle_name": null, "id": 4999}, {"last_name": "Kani", "nugget": "None", "first_name": "Iraj", "middle_name": null, "id": 5003}, {"last_name": "Derosa", "nugget": "None", "first_name": "David", "middle_name": "F.", "id": 5004}, {"last_name": "Ozer", "nugget": "None", "first_name": "Ozalp", "middle_name": null, "id": 5005}, {"last_name": "Luss", "nugget": "None", "first_name": "Hanan", "middle_name": "", "id": 5011}, {"last_name": "Hueter", "nugget": "None", "first_name": "Irene", "middle_name": null, "id": 6359}, {"last_name": "Sadighian", "nugget": "None", "first_name": "Ali", "middle_name": null, "id": 10313}, {"last_name": "Gulley", "nugget": "None", "first_name": "David", "middle_name": null, "id": 10315}, {"last_name": "He", "nugget": "None", "first_name": "Xuedong", "middle_name": null, "id": 10316}, {"last_name": "Liu", "nugget": "None", "first_name": "Yunan", "middle_name": null, "id": 10535}, {"last_name": "Truong", "nugget": "None", "first_name": "Van-Anh", "middle_name": "Anh", "id": 10860}, {"last_name": "Dahlgren", "nugget": "None", "first_name": "Eric", "middle_name": "", "id": 11423}, {"last_name": "Strickland", "nugget": "Silver", "first_name": "Dawn", "middle_name": null, "id": 11575}, {"last_name": "Vora", "nugget": "None", "first_name": "Ashok", "middle_name": "", "id": 12517}]