[{"nugget": "None", "last_name": "Trompetter", "first_name": "Amy", "middle_name": "", "id": 245}, {"nugget": "Silver", "last_name": "Guy", "first_name": "Rebecca", "middle_name": "", "id": 469}, {"nugget": "Silver", "last_name": "Crapotta", "first_name": "James", "middle_name": "", "id": 896}, {"nugget": "None", "last_name": "Amin", "first_name": "Dina", "middle_name": "", "id": 1001}, {"nugget": "None", "last_name": "Partridge", "first_name": "Denny", "middle_name": "", "id": 1127}, {"nugget": "None", "last_name": "Friedman", "first_name": "Steve", "middle_name": "", "id": 1128}, {"nugget": "None", "last_name": "Yi", "first_name": "Quan", "middle_name": "", "id": 1871}, {"nugget": "Silver", "last_name": "Rosenblum", "first_name": "Harry", "middle_name": "", "id": 1942}, {"nugget": "None", "last_name": "Flatmo", "first_name": "Erik", "middle_name": "", "id": 2004}, {"nugget": "Silver", "last_name": "Cobrin", "first_name": "Pamela", "middle_name": "", "id": 2177}, {"nugget": "None", "last_name": "Cairo", "first_name": "Joeseph", "middle_name": "", "id": 2331}, {"nugget": "None", "last_name": "Burney", "first_name": "Christopher", "middle_name": "", "id": 3138}, {"nugget": "Silver", "last_name": "Zito", "first_name": "Ralph", "middle_name": "", "id": 3193}, {"nugget": "None", "last_name": "Winkler", "first_name": "Gregory", "middle_name": "", "id": 3317}, {"nugget": "Silver", "last_name": "Chaikelson", "first_name": "Steven", "middle_name": "", "id": 3344}, {"nugget": "Silver", "last_name": "Goldmark", "first_name": "Sandra", "middle_name": "", "id": 3381}, {"nugget": "None", "last_name": "Waterman", "first_name": "Wendy", "middle_name": "", "id": 3385}, {"nugget": "Gold", "last_name": "Worthen", "first_name": "William", "middle_name": null, "id": 3992}, {"nugget": "None", "last_name": "McMath", "first_name": "Stacey", "middle_name": null, "id": 6398}, {"nugget": "None", "last_name": "Reagan", "first_name": "Alice", "middle_name": null, "id": 7765}, {"nugget": "None", "last_name": "Greene", "first_name": "Charise", "middle_name": null, "id": 9944}, {"nugget": "None", "last_name": "Mustamaki", "first_name": "Piia", "middle_name": null, "id": 9945}, {"nugget": "None", "last_name": "Mitra", "first_name": "Shayoni", "middle_name": null, "id": 10543}, {"nugget": "None", "last_name": "Bartholomai", "first_name": "Linda", "middle_name": "", "id": 12897}]